{
  "说明摘要": "中央汇金持仓数据来源：基金定期报告。此处为截至2025年报（2025-12-31）数据。两个主体：中央汇金投资 + 中央汇金资产。",
  "数据来源": "同花顺iNews 基金2025年年报分析; 中国证券报/东方财富 2025年四季报分析",
  "更新日期": "2025-12-31",
  "披露日期": "2026-03-31",
  "持仓": {
    "510050": {
      "名称": "华夏上证50ETF",
      "汇金总持股(亿)": 487.59,
      "数据来源": "汇金投资287.92亿+汇金资产199.67亿, 2025年年报/四季报",
      "来源公告": "https://fund.eastmoney.com/f10/gglj_510050.html#spy_2025"
    },
    "510300": {
      "名称": "华泰柏瑞沪深300ETF",
      "汇金总持股(亿)": 735.13,
      "数据来源": "汇金投资356.55亿+汇金资产378.58亿, 2025年年报/四季报",
      "来源公告": "https://fund.eastmoney.com/f10/gglj_510300.html#spy_2025"
    },
    "159919": {
      "名称": "嘉实沪深300ETF",
      "汇金总持股(亿)": 354.98,
      "数据来源": "汇金投资195.44亿+汇金资产159.55亿, 2025年年报/四季报",
      "来源公告": "https://fund.eastmoney.com/f10/gglj_159919.html#spy_2025"
    },
    "510330": {
      "名称": "华夏沪深300ETF",
      "汇金总持股(亿)": 420.28,
      "数据来源": "汇金投资209.37亿+汇金资产210.91亿, 2025年年报/四季报",
      "来源公告": "https://fund.eastmoney.com/f10/gglj_510330.html#spy_2025"
    },
    "510500": {
      "名称": "南方中证500ETF",
      "汇金总持股(亿)": 82.35,
      "数据来源": "汇金投资82.35亿, 2025年年报",
      "来源公告": "https://fund.eastmoney.com/f10/gglj_510500.html#spy_2025"
    },
    "512500": {
      "名称": "华夏中证500ETF",
      "汇金总持股(亿)": 20.51,
      "数据来源": "汇金投资20.51亿, 2025年年报",
      "来源公告": "https://fund.eastmoney.com/f10/gglj_512500.html#spy_2025"
    },
    "159922": {
      "名称": "嘉实中证500ETF",
      "汇金总持股(亿)": 23.11,
      "数据来源": "汇金投资23.11亿, 2025年年报",
      "来源公告": "https://fund.eastmoney.com/f10/gglj_159922.html#spy_2025"
    },
    "512100": {
      "名称": "南方中证1000ETF",
      "汇金总持股(亿)": 221.69,
      "数据来源": "汇金投资221.69亿, 2025年年报",
      "来源公告": "https://fund.eastmoney.com/f10/gglj_512100.html#spy_2025"
    },
    "159845": {
      "名称": "华夏中证1000ETF",
      "汇金总持股(亿)": 137.26,
      "数据来源": "汇金投资137.26亿, 2025年年报",
      "来源公告": "https://fund.eastmoney.com/f10/gglj_159845.html#spy_2025"
    },
    "510180": {
      "名称": "上证180ETF",
      "汇金总持股(亿)": 52.32,
      "数据来源": "汇金投资52.32亿, 2025年年报",
      "来源公告": "https://fund.eastmoney.com/f10/gglj_510180.html#spy_2025"
    },
    "159915": {
      "名称": "易方达创业板ETF",
      "汇金总持股(亿)": 170.20,
      "数据来源": "汇金投资170.20亿, 2025年年报",
      "来源公告": "https://fund.eastmoney.com/f10/gglj_159915.html#spy_2025"
    },
    "159952": {
      "名称": "广发创业板ETF",
      "汇金总持股(亿)": 10.91,
      "数据来源": "汇金投资10.91亿, 2025年年报",
      "来源公告": "https://fund.eastmoney.com/f10/gglj_159952.html#spy_2025"
    },
    "510230": {
      "名称": "国泰上证180金融ETF",
      "汇金总持股(亿)": 25.635605,
      "披露日总份额(亿)": 33.03808035,
      "汇金占比": 0.7759411178985162,
      "数据来源": "中央汇金投资有限责任公司持有2,563,560,500份, 2025年年报第61页",
      "来源公告": "https://notice.10jqka.com.cn/api/pdf/bcf9b3f4e8c494d8.pdf"
    },
    "588080": {
      "名称": "易方达科创板50ETF",
      "汇金总持股(亿)": 216.07,
      "数据来源": "汇金投资216.07亿, 2025年年报",
      "来源公告": "https://fund.eastmoney.com/f10/gglj_588080.html#spy_2025"
    },
    "588000": {
      "名称": "华夏科创50ETF",
      "汇金总持股(亿)": null,
      "数据来源": "2025年年报前十名基金份额持有人未见中央汇金；直接H0未确认，保持blocked待人工复核",
      "来源公告": "https://stockmc.xueqiu.com/202603/588000_20260331_65O5.pdf"
    }
  }
}
